{
    "intro": "I have a strong passion for continuous learning and enjoy exploring emerging technologies.\nThese are some  Languages, Technologies, Tools, and Platforms I have expertise in and am actively pursuing for further mastery:",
    "skills": [{
     
            "title": "Languages & Databases",
            "items" : [
     
                {
                    "icon": "images/skills/java.png",
                    "title": "Java"
                },
                {
                    "icon": "images/skills/kotlin.png",
                    "title": "Kotlin"
                },
                {
                    "icon": "images/skills/dart.png",
                    "title": "Dart"
                },
                {
                    "icon": "images/skills/c-plus-plus.svg",
                    "title": "C++"
                },
                {
                    "icon": "images/skills/sql.png",
                    "title": "SQL"
                },
                {
                    "icon": "images/skills/mysql.png",
                    "title": "MySQL"
                },
                {
                    "icon": "images/skills/no-sql.png",
                    "title": "NoSQL"
                }
        ]},
        {
            "title": "Frameworks & Technologies",
            "items" : [
                {
                    "icon": "images/skills/android_new.png",
                    "title": "Android"
                },
                {
                    "icon": "images/skills/flutter.png",
                    "title": "Flutter"
                },
                {
                    "icon": "images/skills/firebase.png",
                    "title": "FireBase"
                },
                {
                    "icon": "images/skills/nodejs.png",
                    "title": "Node.js"
                },
                {
                    "icon": "images/skills/mongo-db.png",
                    "title": "MongoDB"
                },
                {
                    "icon": "images/skills/getx.png",
                    "title": "GetX"
                },
                {
                    "icon": "images/skills/riverpod.png",
                    "title": "Riverpod"
                },
                {
                    "icon": "images/skills/bloc.png",
                    "title": "Bloc (soon)"
                }
            ]
        },
        {
            "title" : "Tools & Platforms",
            "items": [
                {
                    "icon": "images/skills/android-studio.png",
                    "title": "Android Studio"
                },
                {
                    "icon": "images/skills/git.png",
                    "title": "Git"
                },
                {
                    "icon": "images/skills/github.png",
                    "title": "Github"
                },
                {
                    "icon": "images/skills/docker.png",
                    "title": "Docker"
                }
            ]
    }
]}
